chiral_db_grpc_client/__init__.py
chiral_db_grpc_client/chiral_db_pb2.py
chiral_db_grpc_client/chiral_db_pb2_grpc.py
chiral_db_grpc_client/client.py
chiral_db_grpc_client-0.0.5.dist-info/LICENSE
chiral_db_grpc_client-0.0.5.dist-info/METADATA
chiral_db_grpc_client-0.0.5.dist-info/WHEEL
chiral_db_grpc_client-0.0.5.dist-info/top_level.txt
chiral_db_grpc_client-0.0.5.dist-info/RECORD
