Metadata-Version: 2.1
Name: chiral-db-grpc-client
Version: 0.0.5
Summary: ChiralDB gRPC Client in Python
Home-page: https://github.com/chiral-data/chiral-db-grpc-client
Author: Qin Wan
Author-email: rogerwq@gmail.com
License: MIT
Platform: UNKNOWN
Classifier: Programming Language :: Python :: 3
Classifier: License :: OSI Approved :: MIT License
Classifier: Operating System :: OS Independent
License-File: LICENSE
